{
  "Distances": [
    {
      "Buildings": [
        " EX",
        " SK"
      ],
      "WalkingTime": "00:17:00",
      "WalkingDistance": {
        "Kilometers": 1.4,
        "Meters": 0.0,
        "Centimeters": 0.0,
        "Millimeters": 0.0
      },
      "CyclingTime": "00:00:00",
      "CyclingDistance": {
        "Kilometers": 0.0,
        "Meters": 0.0,
        "Centimeters": 0.0,
        "Millimeters": 0.0
      },
      "DrivingTime": "00:00:00",
      "DrivingDistance": {
        "Kilometers": 0.0,
        "Meters": 0.0,
        "Centimeters": 0.0,
        "Millimeters": 0.0
      }
    },
    {
      "Buildings": [
        " EX",
        " FC"
      ],
      "WalkingTime": "00:12:00",
      "WalkingDistance": {
        "Kilometers": 1.0,
        "Meters": 0.0,
        "Centimeters": 0.0,
        "Millimeters": 0.0
      },
      "CyclingTime": "00:00:00",
      "CyclingDistance": {
        "Kilometers": 0.0,
        "Meters": 0.0,
        "Centimeters": 0.0,
        "Millimeters": 0.0
      },
      "DrivingTime": "00:00:00",
      "DrivingDistance": {
        "Kilometers": 0.0,
        "Meters": 0.0,
        "Centimeters": 0.0,
        "Millimeters": 0.0
      }
    },
    {
      "Buildings": [
        " EX",
        " LW"
      ],
      "WalkingTime": "00:13:00",
      "WalkingDistance": {
        "Kilometers": 1.0,
        "Meters": 0.0,
        "Centimeters": 0.0,
        "Millimeters": 0.0
      },
      "CyclingTime": "00:00:00",
      "CyclingDistance": {
        "Kilometers": 0.0,
        "Meters": 0.0,
        "Centimeters": 0.0,
        "Millimeters": 0.0
      },
      "DrivingTime": "00:00:00",
      "DrivingDistance": {
        "Kilometers": 0.0,
        "Meters": 0.0,
        "Centimeters": 0.0,
        "Millimeters": 0.0
      }
    },
    {
      "Buildings": [
        " EX",
        " FH"
      ],
      "WalkingTime": "00:15:00",
      "WalkingDistance": {
        "Kilometers": 1.1,
        "Meters": 0.0,
        "Centimeters": 0.0,
        "Millimeters": 0.0
      },
      "CyclingTime": "00:00:00",
      "CyclingDistance": {
        "Kilometers": 0.0,
        "Meters": 0.0,
        "Centimeters": 0.0,
        "Millimeters": 0.0
      },
      "DrivingTime": "00:00:00",
      "DrivingDistance": {
        "Kilometers": 0.0,
        "Meters": 0.0,
        "Centimeters": 0.0,
        "Millimeters": 0.0
      }
    },
    {
      "Buildings": [
        " EX",
        " LG"
      ],
      "WalkingTime": "00:16:00",
      "WalkingDistance": {
        "Kilometers": 1.2,
        "Meters": 0.0,
        "Centimeters": 0.0,
        "Millimeters": 0.0
      },
      "CyclingTime": "00:00:00",
      "CyclingDistance": {
        "Kilometers": 0.0,
        "Meters": 0.0,
        "Centimeters": 0.0,
        "Millimeters": 0.0
      },
      "DrivingTime": "00:00:00",
      "DrivingDistance": {
        "Kilometers": 0.0,
        "Meters": 0.0,
        "Centimeters": 0.0,
        "Millimeters": 0.0
      }
    },
    {
      "Buildings": [
        " EX",
        " FI"
      ],
      "WalkingTime": "00:05:00",
      "WalkingDistance": {
        "Kilometers": 0.4,
        "Meters": 0.0,
        "Centimeters": 0.0,
        "Millimeters": 0.0
      },
      "CyclingTime": "00:00:00",
      "CyclingDistance": {
        "Kilometers": 0.0,
        "Meters": 0.0,
        "Centimeters": 0.0,
        "Millimeters": 0.0
      },
      "DrivingTime": "00:00:00",
      "DrivingDistance": {
        "Kilometers": 0.0,
        "Meters": 0.0,
        "Centimeters": 0.0,
        "Millimeters": 0.0
      }
    },
    {
      "Buildings": [
        " EX",
        " FS"
      ],
      "WalkingTime": "00:13:00",
      "WalkingDistance": {
        "Kilometers": 1.0,
        "Meters": 0.0,
        "Centimeters": 0.0,
        "Millimeters": 0.0
      },
      "CyclingTime": "00:00:00",
      "CyclingDistance": {
        "Kilometers": 0.0,
        "Meters": 0.0,
        "Centimeters": 0.0,
        "Millimeters": 0.0
      },
      "DrivingTime": "00:00:00",
      "DrivingDistance": {
        "Kilometers": 0.0,
        "Meters": 0.0,
        "Centimeters": 0.0,
        "Millimeters": 0.0
      }
    },
    {
      "Buildings": [
        " EX",
        " FG"
      ],
      "WalkingTime": "00:02:00",
      "WalkingDistance": {
        "Kilometers": 0.2,
        "Meters": 0.0,
        "Centimeters": 0.0,
        "Millimeters": 0.0
      },
      "CyclingTime": "00:00:00",
      "CyclingDistance": {
        "Kilometers": 0.0,
        "Meters": 0.0,
        "Centimeters": 0.0,
        "Millimeters": 0.0
      },
      "DrivingTime": "00:00:00",
      "DrivingDistance": {
        "Kilometers": 0.0,
        "Meters": 0.0,
        "Centimeters": 0.0,
        "Millimeters": 0.0
      }
    },
    {
      "Buildings": [
        " EX",
        " BH"
      ],
      "WalkingTime": "00:14:00",
      "WalkingDistance": {
        "Kilometers": 1.1,
        "Meters": 0.0,
        "Centimeters": 0.0,
        "Millimeters": 0.0
      },
      "CyclingTime": "00:00:00",
      "CyclingDistance": {
        "Kilometers": 0.0,
        "Meters": 0.0,
        "Centimeters": 0.0,
        "Millimeters": 0.0
      },
      "DrivingTime": "00:00:00",
      "DrivingDistance": {
        "Kilometers": 0.0,
        "Meters": 0.0,
        "Centimeters": 0.0,
        "Millimeters": 0.0
      }
    },
    {
      "Buildings": [
        " EX",
        " GA"
      ],
      "WalkingTime": "00:06:00",
      "WalkingDistance": {
        "Kilometers": 0.4,
        "Meters": 0.0,
        "Centimeters": 0.0,
        "Millimeters": 0.0
      },
      "CyclingTime": "00:00:00",
      "CyclingDistance": {
        "Kilometers": 0.0,
        "Meters": 0.0,
        "Centimeters": 0.0,
        "Millimeters": 0.0
      },
      "DrivingTime": "00:00:00",
      "DrivingDistance": {
        "Kilometers": 0.0,
        "Meters": 0.0,
        "Centimeters": 0.0,
        "Millimeters": 0.0
      }
    },
    {
      "Buildings": [
        " EX",
        " GB"
      ],
      "WalkingTime": "00:06:00",
      "WalkingDistance": {
        "Kilometers": 0.4,
        "Meters": 0.0,
        "Centimeters": 0.0,
        "Millimeters": 0.0
      },
      "CyclingTime": "00:00:00",
      "CyclingDistance": {
        "Kilometers": 0.0,
        "Meters": 0.0,
        "Centimeters": 0.0,
        "Millimeters": 0.0
      },
      "DrivingTime": "00:00:00",
      "DrivingDistance": {
        "Kilometers": 0.0,
        "Meters": 0.0,
        "Centimeters": 0.0,
        "Millimeters": 0.0
      }
    },
    {
      "Buildings": [
        " EX",
        " GI"
      ],
      "WalkingTime": "00:13:00",
      "WalkingDistance": {
        "Kilometers": 1.0,
        "Meters": 0.0,
        "Centimeters": 0.0,
        "Millimeters": 0.0
      },
      "CyclingTime": "00:00:00",
      "CyclingDistance": {
        "Kilometers": 0.0,
        "Meters": 0.0,
        "Centimeters": 0.0,
        "Millimeters": 0.0
      },
      "DrivingTime": "00:00:00",
      "DrivingDistance": {
        "Kilometers": 0.0,
        "Meters": 0.0,
        "Centimeters": 0.0,
        "Millimeters": 0.0
      }
    },
    {
      "Buildings": [
        " EX",
        " LA"
      ],
      "WalkingTime": "00:13:00",
      "WalkingDistance": {
        "Kilometers": 1.0,
        "Meters": 0.0,
        "Centimeters": 0.0,
        "Millimeters": 0.0
      },
      "CyclingTime": "00:00:00",
      "CyclingDistance": {
        "Kilometers": 0.0,
        "Meters": 0.0,
        "Centimeters": 0.0,
        "Millimeters": 0.0
      },
      "DrivingTime": "00:00:00",
      "DrivingDistance": {
        "Kilometers": 0.0,
        "Meters": 0.0,
        "Centimeters": 0.0,
        "Millimeters": 0.0
      }
    },
    {
      "Buildings": [
        " EX",
        " SM"
      ],
      "WalkingTime": "00:07:00",
      "WalkingDistance": {
        "Kilometers": 0.5,
        "Meters": 0.0,
        "Centimeters": 0.0,
        "Millimeters": 0.0
      },
      "CyclingTime": "00:00:00",
      "CyclingDistance": {
        "Kilometers": 0.0,
        "Meters": 0.0,
        "Centimeters": 0.0,
        "Millimeters": 0.0
      },
      "DrivingTime": "00:00:00",
      "DrivingDistance": {
        "Kilometers": 0.0,
        "Meters": 0.0,
        "Centimeters": 0.0,
        "Millimeters": 0.0
      }
    },
    {
      "Buildings": [
        " EX",
        " GH"
      ],
      "WalkingTime": "00:15:00",
      "WalkingDistance": {
        "Kilometers": 1.1,
        "Meters": 0.0,
        "Centimeters": 0.0,
        "Millimeters": 0.0
      },
      "CyclingTime": "00:00:00",
      "CyclingDistance": {
        "Kilometers": 0.0,
        "Meters": 0.0,
        "Centimeters": 0.0,
        "Millimeters": 0.0
      },
      "DrivingTime": "00:00:00",
      "DrivingDistance": {
        "Kilometers": 0.0,
        "Meters": 0.0,
        "Centimeters": 0.0,
        "Millimeters": 0.0
      }
    },
    {
      "Buildings": [
        " EX",
        " GO"
      ],
      "WalkingTime": "00:15:00",
      "WalkingDistance": {
        "Kilometers": 1.2,
        "Meters": 0.0,
        "Centimeters": 0.0,
        "Millimeters": 0.0
      },
      "CyclingTime": "00:00:00",
      "CyclingDistance": {
        "Kilometers": 0.0,
        "Meters": 0.0,
        "Centimeters": 0.0,
        "Millimeters": 0.0
      },
      "DrivingTime": "00:00:00",
      "DrivingDistance": {
        "Kilometers": 0.0,
        "Meters": 0.0,
        "Centimeters": 0.0,
        "Millimeters": 0.0
      }
    },
    {
      "Buildings": [
        " EX",
        " GC"
      ],
      "WalkingTime": "00:17:00",
      "WalkingDistance": {
        "Kilometers": 1.3,
        "Meters": 0.0,
        "Centimeters": 0.0,
        "Millimeters": 0.0
      },
      "CyclingTime": "00:00:00",
      "CyclingDistance": {
        "Kilometers": 0.0,
        "Meters": 0.0,
        "Centimeters": 0.0,
        "Millimeters": 0.0
      },
      "DrivingTime": "00:00:00",
      "DrivingDistance": {
        "Kilometers": 0.0,
        "Meters": 0.0,
        "Centimeters": 0.0,
        "Millimeters": 0.0
      }
    },
    {
      "Buildings": [
        " EX",
        " GD"
      ],
      "WalkingTime": "00:14:00",
      "WalkingDistance": {
        "Kilometers": 1.1,
        "Meters": 0.0,
        "Centimeters": 0.0,
        "Millimeters": 0.0
      },
      "CyclingTime": "00:00:00",
      "CyclingDistance": {
        "Kilometers": 0.0,
        "Meters": 0.0,
        "Centimeters": 0.0,
        "Millimeters": 0.0
      },
      "DrivingTime": "00:00:00",
      "DrivingDistance": {
        "Kilometers": 0.0,
        "Meters": 0.0,
        "Centimeters": 0.0,
        "Millimeters": 0.0
      }
    },
    {
      "Buildings": [
        " EX",
        " GU"
      ],
      "WalkingTime": "00:10:00",
      "WalkingDistance": {
        "Kilometers": 0.8,
        "Meters": 0.0,
        "Centimeters": 0.0,
        "Millimeters": 0.0
      },
      "CyclingTime": "00:00:00",
      "CyclingDistance": {
        "Kilometers": 0.0,
        "Meters": 0.0,
        "Centimeters": 0.0,
        "Millimeters": 0.0
      },
      "DrivingTime": "00:00:00",
      "DrivingDistance": {
        "Kilometers": 0.0,
        "Meters": 0.0,
        "Centimeters": 0.0,
        "Millimeters": 0.0
      }
    },
    {
      "Buildings": [
        " EX",
        " HH"
      ],
      "WalkingTime": "00:09:00",
      "WalkingDistance": {
        "Kilometers": 0.7,
        "Meters": 0.0,
        "Centimeters": 0.0,
        "Millimeters": 0.0
      },
      "CyclingTime": "00:00:00",
      "CyclingDistance": {
        "Kilometers": 0.0,
        "Meters": 0.0,
        "Centimeters": 0.0,
        "Millimeters": 0.0
      },
      "DrivingTime": "00:00:00",
      "DrivingDistance": {
        "Kilometers": 0.0,
        "Meters": 0.0,
        "Centimeters": 0.0,
        "Millimeters": 0.0
      }
    },
    {
      "Buildings": [
        " EX",
        " HA"
      ],
      "WalkingTime": "00:01:00",
      "WalkingDistance": {
        "Kilometers": 0.1,
        "Meters": 0.0,
        "Centimeters": 0.0,
        "Millimeters": 0.0
      },
      "CyclingTime": "00:00:00",
      "CyclingDistance": {
        "Kilometers": 0.0,
        "Meters": 0.0,
        "Centimeters": 0.0,
        "Millimeters": 0.0
      },
      "DrivingTime": "00:00:00",
      "DrivingDistance": {
        "Kilometers": 0.0,
        "Meters": 0.0,
        "Centimeters": 0.0,
        "Millimeters": 0.0
      }
    },
    {
      "Buildings": [
        " EX",
        " HS"
      ],
      "WalkingTime": "00:02:00",
      "WalkingDistance": {
        "Kilometers": 0.1,
        "Meters": 0.0,
        "Centimeters": 0.0,
        "Millimeters": 0.0
      },
      "CyclingTime": "00:00:00",
      "CyclingDistance": {
        "Kilometers": 0.0,
        "Meters": 0.0,
        "Centimeters": 0.0,
        "Millimeters": 0.0
      },
      "DrivingTime": "00:00:00",
      "DrivingDistance": {
        "Kilometers": 0.0,
        "Meters": 0.0,
        "Centimeters": 0.0,
        "Millimeters": 0.0
      }
    },
    {
      "Buildings": [
        " EX",
        " HU"
      ],
      "WalkingTime": "00:08:00",
      "WalkingDistance": {
        "Kilometers": 0.6,
        "Meters": 0.0,
        "Centimeters": 0.0,
        "Millimeters": 0.0
      },
      "CyclingTime": "00:00:00",
      "CyclingDistance": {
        "Kilometers": 0.0,
        "Meters": 0.0,
        "Centimeters": 0.0,
        "Millimeters": 0.0
      },
      "DrivingTime": "00:00:00",
      "DrivingDistance": {
        "Kilometers": 0.0,
        "Meters": 0.0,
        "Centimeters": 0.0,
        "Millimeters": 0.0
      }
    },
    {
      "Buildings": [
        " EX",
        " CA"
      ],
      "WalkingTime": "00:14:00",
      "WalkingDistance": {
        "Kilometers": 1.1,
        "Meters": 0.0,
        "Centimeters": 0.0,
        "Millimeters": 0.0
      },
      "CyclingTime": "00:00:00",
      "CyclingDistance": {
        "Kilometers": 0.0,
        "Meters": 0.0,
        "Centimeters": 0.0,
        "Millimeters": 0.0
      },
      "DrivingTime": "00:00:00",
      "DrivingDistance": {
        "Kilometers": 0.0,
        "Meters": 0.0,
        "Centimeters": 0.0,
        "Millimeters": 0.0
      }
    },
    {
      "Buildings": [
        " EX",
        " IN"
      ],
      "WalkingTime": "00:15:00",
      "WalkingDistance": {
        "Kilometers": 1.1,
        "Meters": 0.0,
        "Centimeters": 0.0,
        "Millimeters": 0.0
      },
      "CyclingTime": "00:00:00",
      "CyclingDistance": {
        "Kilometers": 0.0,
        "Meters": 0.0,
        "Centimeters": 0.0,
        "Millimeters": 0.0
      },
      "DrivingTime": "00:00:00",
      "DrivingDistance": {
        "Kilometers": 0.0,
        "Meters": 0.0,
        "Centimeters": 0.0,
        "Millimeters": 0.0
      }
    },
    {
      "Buildings": [
        " EX",
        " IS"
      ],
      "WalkingTime": "00:15:00",
      "WalkingDistance": {
        "Kilometers": 1.1,
        "Meters": 0.0,
        "Centimeters": 0.0,
        "Millimeters": 0.0
      },
      "CyclingTime": "00:00:00",
      "CyclingDistance": {
        "Kilometers": 0.0,
        "Meters": 0.0,
        "Centimeters": 0.0,
        "Millimeters": 0.0
      },
      "DrivingTime": "00:00:00",
      "DrivingDistance": {
        "Kilometers": 0.0,
        "Meters": 0.0,
        "Centimeters": 0.0,
        "Millimeters": 0.0
      }
    },
    {
      "Buildings": [
        " EX",
        " BT"
      ],
      "WalkingTime": "00:17:00",
      "WalkingDistance": {
        "Kilometers": 1.3,
        "Meters": 0.0,
        "Centimeters": 0.0,
        "Millimeters": 0.0
      },
      "CyclingTime": "00:00:00",
      "CyclingDistance": {
        "Kilometers": 0.0,
        "Meters": 0.0,
        "Centimeters": 0.0,
        "Millimeters": 0.0
      },
      "DrivingTime": "00:00:00",
      "DrivingDistance": {
        "Kilometers": 0.0,
        "Meters": 0.0,
        "Centimeters": 0.0,
        "Millimeters": 0.0
      }
    },
    {
      "Buildings": [
        " EX",
        " KL"
      ],
      "WalkingTime": "00:14:00",
      "WalkingDistance": {
        "Kilometers": 1.1,
        "Meters": 0.0,
        "Centimeters": 0.0,
        "Millimeters": 0.0
      },
      "CyclingTime": "00:00:00",
      "CyclingDistance": {
        "Kilometers": 0.0,
        "Meters": 0.0,
        "Centimeters": 0.0,
        "Millimeters": 0.0
      },
      "DrivingTime": "00:00:00",
      "DrivingDistance": {
        "Kilometers": 0.0,
        "Meters": 0.0,
        "Centimeters": 0.0,
        "Millimeters": 0.0
      }
    },
    {
      "Buildings": [
        " EX",
        " DR"
      ],
      "WalkingTime": "00:07:00",
      "WalkingDistance": {
        "Kilometers": 0.6,
        "Meters": 0.0,
        "Centimeters": 0.0,
        "Millimeters": 0.0
      },
      "CyclingTime": "00:00:00",
      "CyclingDistance": {
        "Kilometers": 0.0,
        "Meters": 0.0,
        "Centimeters": 0.0,
        "Millimeters": 0.0
      },
      "DrivingTime": "00:00:00",
      "DrivingDistance": {
        "Kilometers": 0.0,
        "Meters": 0.0,
        "Centimeters": 0.0,
        "Millimeters": 0.0
      }
    },
    {
      "Buildings": [
        " EX",
        " JH"
      ],
      "WalkingTime": "00:17:00",
      "WalkingDistance": {
        "Kilometers": 1.3,
        "Meters": 0.0,
        "Centimeters": 0.0,
        "Millimeters": 0.0
      },
      "CyclingTime": "00:00:00",
      "CyclingDistance": {
        "Kilometers": 0.0,
        "Meters": 0.0,
        "Centimeters": 0.0,
        "Millimeters": 0.0
      },
      "DrivingTime": "00:00:00",
      "DrivingDistance": {
        "Kilometers": 0.0,
        "Meters": 0.0,
        "Centimeters": 0.0,
        "Millimeters": 0.0
      }
    },
    {
      "Buildings": [
        " EX",
        " RL"
      ],
      "WalkingTime": "00:13:00",
      "WalkingDistance": {
        "Kilometers": 1.0,
        "Meters": 0.0,
        "Centimeters": 0.0,
        "Millimeters": 0.0
      },
      "CyclingTime": "00:00:00",
      "CyclingDistance": {
        "Kilometers": 0.0,
        "Meters": 0.0,
        "Centimeters": 0.0,
        "Millimeters": 0.0
      },
      "DrivingTime": "00:00:00",
      "DrivingDistance": {
        "Kilometers": 0.0,
        "Meters": 0.0,
        "Centimeters": 0.0,
        "Millimeters": 0.0
      }
    },
    {
      "Buildings": [
        " EX",
        " KX"
      ],
      "WalkingTime": "00:08:00",
      "WalkingDistance": {
        "Kilometers": 0.6,
        "Meters": 0.0,
        "Centimeters": 0.0,
        "Millimeters": 0.0
      },
      "CyclingTime": "00:00:00",
      "CyclingDistance": {
        "Kilometers": 0.0,
        "Meters": 0.0,
        "Centimeters": 0.0,
        "Millimeters": 0.0
      },
      "DrivingTime": "00:00:00",
      "DrivingDistance": {
        "Kilometers": 0.0,
        "Meters": 0.0,
        "Centimeters": 0.0,
        "Millimeters": 0.0
      }
    },
    {
      "Buildings": [
        " EX",
        " KP"
      ],
      "WalkingTime": "00:11:00",
      "WalkingDistance": {
        "Kilometers": 0.8,
        "Meters": 0.0,
        "Centimeters": 0.0,
        "Millimeters": 0.0
      },
      "CyclingTime": "00:00:00",
      "CyclingDistance": {
        "Kilometers": 0.0,
        "Meters": 0.0,
        "Centimeters": 0.0,
        "Millimeters": 0.0
      },
      "DrivingTime": "00:00:00",
      "DrivingDistance": {
        "Kilometers": 0.0,
        "Meters": 0.0,
        "Centimeters": 0.0,
        "Millimeters": 0.0
      }
    },
    {
      "Buildings": [
        " EX",
        " KS"
      ],
      "WalkingTime": "00:05:00",
      "WalkingDistance": {
        "Kilometers": 0.4,
        "Meters": 0.0,
        "Centimeters": 0.0,
        "Millimeters": 0.0
      },
      "CyclingTime": "00:00:00",
      "CyclingDistance": {
        "Kilometers": 0.0,
        "Meters": 0.0,
        "Centimeters": 0.0,
        "Millimeters": 0.0
      },
      "DrivingTime": "00:00:00",
      "DrivingDistance": {
        "Kilometers": 0.0,
        "Meters": 0.0,
        "Centimeters": 0.0,
        "Millimeters": 0.0
      }
    },
    {
      "Buildings": [
        " EX",
        " LM"
      ],
      "WalkingTime": "00:09:00",
      "WalkingDistance": {
        "Kilometers": 0.7,
        "Meters": 0.0,
        "Centimeters": 0.0,
        "Millimeters": 0.0
      },
      "CyclingTime": "00:00:00",
      "CyclingDistance": {
        "Kilometers": 0.0,
        "Meters": 0.0,
        "Centimeters": 0.0,
        "Millimeters": 0.0
      },
      "DrivingTime": "00:00:00",
      "DrivingDistance": {
        "Kilometers": 0.0,
        "Meters": 0.0,
        "Centimeters": 0.0,
        "Millimeters": 0.0
      }
    },
    {
      "Buildings": [
        " EX",
        " MB"
      ],
      "WalkingTime": "00:01:00",
      "WalkingDistance": {
        "Kilometers": 0.1,
        "Meters": 0.0,
        "Centimeters": 0.0,
        "Millimeters": 0.0
      },
      "CyclingTime": "00:00:00",
      "CyclingDistance": {
        "Kilometers": 0.0,
        "Meters": 0.0,
        "Centimeters": 0.0,
        "Millimeters": 0.0
      },
      "DrivingTime": "00:00:00",
      "DrivingDistance": {
        "Kilometers": 0.0,
        "Meters": 0.0,
        "Centimeters": 0.0,
        "Millimeters": 0.0
      }
    },
    {
      "Buildings": [
        " EX",
        " WR"
      ],
      "WalkingTime": "00:26:00",
      "WalkingDistance": {
        "Kilometers": 2.1,
        "Meters": 0.0,
        "Centimeters": 0.0,
        "Millimeters": 0.0
      },
      "CyclingTime": "00:00:00",
      "CyclingDistance": {
        "Kilometers": 0.0,
        "Meters": 0.0,
        "Centimeters": 0.0,
        "Millimeters": 0.0
      },
      "DrivingTime": "00:00:00",
      "DrivingDistance": {
        "Kilometers": 0.0,
        "Meters": 0.0,
        "Centimeters": 0.0,
        "Millimeters": 0.0
      }
    },
    {
      "Buildings": [
        " EX",
        " PB"
      ],
      "WalkingTime": "00:03:00",
      "WalkingDistance": {
        "Kilometers": 0.2,
        "Meters": 0.0,
        "Centimeters": 0.0,
        "Millimeters": 0.0
      },
      "CyclingTime": "00:00:00",
      "CyclingDistance": {
        "Kilometers": 0.0,
        "Meters": 0.0,
        "Centimeters": 0.0,
        "Millimeters": 0.0
      },
      "DrivingTime": "00:00:00",
      "DrivingDistance": {
        "Kilometers": 0.0,
        "Meters": 0.0,
        "Centimeters": 0.0,
        "Millimeters": 0.0
      }
    },
    {
      "Buildings": [
        " EX",
        " LI"
      ],
      "WalkingTime": "00:17:00",
      "WalkingDistance": {
        "Kilometers": 1.3,
        "Meters": 0.0,
        "Centimeters": 0.0,
        "Millimeters": 0.0
      },
      "CyclingTime": "00:00:00",
      "CyclingDistance": {
        "Kilometers": 0.0,
        "Meters": 0.0,
        "Centimeters": 0.0,
        "Millimeters": 0.0
      },
      "DrivingTime": "00:00:00",
      "DrivingDistance": {
        "Kilometers": 0.0,
        "Meters": 0.0,
        "Centimeters": 0.0,
        "Millimeters": 0.0
      }
    },
    {
      "Buildings": [
        " EX",
        " LC"
      ],
      "WalkingTime": "00:17:00",
      "WalkingDistance": {
        "Kilometers": 1.3,
        "Meters": 0.0,
        "Centimeters": 0.0,
        "Millimeters": 0.0
      },
      "CyclingTime": "00:00:00",
      "CyclingDistance": {
        "Kilometers": 0.0,
        "Meters": 0.0,
        "Centimeters": 0.0,
        "Millimeters": 0.0
      },
      "DrivingTime": "00:00:00",
      "DrivingDistance": {
        "Kilometers": 0.0,
        "Meters": 0.0,
        "Centimeters": 0.0,
        "Millimeters": 0.0
      }
    },
    {
      "Buildings": [
        " EX",
        " SO"
      ],
      "WalkingTime": "00:08:00",
      "WalkingDistance": {
        "Kilometers": 0.7,
        "Meters": 0.0,
        "Centimeters": 0.0,
        "Millimeters": 0.0
      },
      "CyclingTime": "00:00:00",
      "CyclingDistance": {
        "Kilometers": 0.0,
        "Meters": 0.0,
        "Centimeters": 0.0,
        "Millimeters": 0.0
      },
      "DrivingTime": "00:00:00",
      "DrivingDistance": {
        "Kilometers": 0.0,
        "Meters": 0.0,
        "Centimeters": 0.0,
        "Millimeters": 0.0
      }
    },
    {
      "Buildings": [
        " EX",
        " GM"
      ],
      "WalkingTime": "00:15:00",
      "WalkingDistance": {
        "Kilometers": 1.1,
        "Meters": 0.0,
        "Centimeters": 0.0,
        "Millimeters": 0.0
      },
      "CyclingTime": "00:00:00",
      "CyclingDistance": {
        "Kilometers": 0.0,
        "Meters": 0.0,
        "Centimeters": 0.0,
        "Millimeters": 0.0
      },
      "DrivingTime": "00:00:00",
      "DrivingDistance": {
        "Kilometers": 0.0,
        "Meters": 0.0,
        "Centimeters": 0.0,
        "Millimeters": 0.0
      }
    },
    {
      "Buildings": [
        " EX",
        " MM"
      ],
      "WalkingTime": "00:09:00",
      "WalkingDistance": {
        "Kilometers": 0.7,
        "Meters": 0.0,
        "Centimeters": 0.0,
        "Millimeters": 0.0
      },
      "CyclingTime": "00:00:00",
      "CyclingDistance": {
        "Kilometers": 0.0,
        "Meters": 0.0,
        "Centimeters": 0.0,
        "Millimeters": 0.0
      },
      "DrivingTime": "00:00:00",
      "DrivingDistance": {
        "Kilometers": 0.0,
        "Meters": 0.0,
        "Centimeters": 0.0,
        "Millimeters": 0.0
      }
    },
    {
      "Buildings": [
        " EX",
        " MG"
      ],
      "WalkingTime": "00:17:00",
      "WalkingDistance": {
        "Kilometers": 1.3,
        "Meters": 0.0,
        "Centimeters": 0.0,
        "Millimeters": 0.0
      },
      "CyclingTime": "00:00:00",
      "CyclingDistance": {
        "Kilometers": 0.0,
        "Meters": 0.0,
        "Centimeters": 0.0,
        "Millimeters": 0.0
      },
      "DrivingTime": "00:00:00",
      "DrivingDistance": {
        "Kilometers": 0.0,
        "Meters": 0.0,
        "Centimeters": 0.0,
        "Millimeters": 0.0
      }
    },
    {
      "Buildings": [
        " EX",
        " MN"
      ],
      "WalkingTime": "00:15:00",
      "WalkingDistance": {
        "Kilometers": 1.1,
        "Meters": 0.0,
        "Centimeters": 0.0,
        "Millimeters": 0.0
      },
      "CyclingTime": "00:00:00",
      "CyclingDistance": {
        "Kilometers": 0.0,
        "Meters": 0.0,
        "Centimeters": 0.0,
        "Millimeters": 0.0
      },
      "DrivingTime": "00:00:00",
      "DrivingDistance": {
        "Kilometers": 0.0,
        "Meters": 0.0,
        "Centimeters": 0.0,
        "Millimeters": 0.0
      }
    },
    {
      "Buildings": [
        " EX",
        " M2"
      ],
      "WalkingTime": "00:05:00",
      "WalkingDistance": {
        "Kilometers": 0.4,
        "Meters": 0.0,
        "Centimeters": 0.0,
        "Millimeters": 0.0
      },
      "CyclingTime": "00:00:00",
      "CyclingDistance": {
        "Kilometers": 0.0,
        "Meters": 0.0,
        "Centimeters": 0.0,
        "Millimeters": 0.0
      },
      "DrivingTime": "00:00:00",
      "DrivingDistance": {
        "Kilometers": 0.0,
        "Meters": 0.0,
        "Centimeters": 0.0,
        "Millimeters": 0.0
      }
    },
    {
      "Buildings": [
        " EX",
        " MA"
      ],
      "WalkingTime": "00:12:00",
      "WalkingDistance": {
        "Kilometers": 0.9,
        "Meters": 0.0,
        "Centimeters": 0.0,
        "Millimeters": 0.0
      },
      "CyclingTime": "00:00:00",
      "CyclingDistance": {
        "Kilometers": 0.0,
        "Meters": 0.0,
        "Centimeters": 0.0,
        "Millimeters": 0.0
      },
      "DrivingTime": "00:00:00",
      "DrivingDistance": {
        "Kilometers": 0.0,
        "Meters": 0.0,
        "Centimeters": 0.0,
        "Millimeters": 0.0
      }
    },
    {
      "Buildings": [
        " EX",
        " GE"
      ],
      "WalkingTime": "00:15:00",
      "WalkingDistance": {
        "Kilometers": 1.1,
        "Meters": 0.0,
        "Centimeters": 0.0,
        "Millimeters": 0.0
      },
      "CyclingTime": "00:00:00",
      "CyclingDistance": {
        "Kilometers": 0.0,
        "Meters": 0.0,
        "Centimeters": 0.0,
        "Millimeters": 0.0
      },
      "DrivingTime": "00:00:00",
      "DrivingDistance": {
        "Kilometers": 0.0,
        "Meters": 0.0,
        "Centimeters": 0.0,
        "Millimeters": 0.0
      }
    },
    {
      "Buildings": [
        " EX",
        " RM"
      ],
      "WalkingTime": "00:01:00",
      "WalkingDistance": {
        "Kilometers": 0.0,
        "Meters": 26.0,
        "Centimeters": 0.0,
        "Millimeters": 0.0
      },
      "CyclingTime": "00:00:00",
      "CyclingDistance": {
        "Kilometers": 0.0,
        "Meters": 0.0,
        "Centimeters": 0.0,
        "Millimeters": 0.0
      },
      "DrivingTime": "00:00:00",
      "DrivingDistance": {
        "Kilometers": 0.0,
        "Meters": 0.0,
        "Centimeters": 0.0,
        "Millimeters": 0.0
      }
    },
    {
      "Buildings": [
        " EX",
        " MZ"
      ],
      "WalkingTime": "00:14:00",
      "WalkingDistance": {
        "Kilometers": 1.1,
        "Meters": 0.0,
        "Centimeters": 0.0,
        "Millimeters": 0.0
      },
      "CyclingTime": "00:00:00",
      "CyclingDistance": {
        "Kilometers": 0.0,
        "Meters": 0.0,
        "Centimeters": 0.0,
        "Millimeters": 0.0
      },
      "DrivingTime": "00:00:00",
      "DrivingDistance": {
        "Kilometers": 0.0,
        "Meters": 0.0,
        "Centimeters": 0.0,
        "Millimeters": 0.0
      }
    },
    {
      "Buildings": [
        " EX",
        " MP"
      ],
      "WalkingTime": "00:10:00",
      "WalkingDistance": {
        "Kilometers": 0.7,
        "Meters": 0.0,
        "Centimeters": 0.0,
        "Millimeters": 0.0
      },
      "CyclingTime": "00:00:00",
      "CyclingDistance": {
        "Kilometers": 0.0,
        "Meters": 0.0,
        "Centimeters": 0.0,
        "Millimeters": 0.0
      },
      "DrivingTime": "00:00:00",
      "DrivingDistance": {
        "Kilometers": 0.0,
        "Meters": 0.0,
        "Centimeters": 0.0,
        "Millimeters": 0.0
      }
    },
    {
      "Buildings": [
        " EX",
        " MR"
      ],
      "WalkingTime": "00:06:00",
      "WalkingDistance": {
        "Kilometers": 0.5,
        "Meters": 0.0,
        "Centimeters": 0.0,
        "Millimeters": 0.0
      },
      "CyclingTime": "00:00:00",
      "CyclingDistance": {
        "Kilometers": 0.0,
        "Meters": 0.0,
        "Centimeters": 0.0,
        "Millimeters": 0.0
      },
      "DrivingTime": "00:00:00",
      "DrivingDistance": {
        "Kilometers": 0.0,
        "Meters": 0.0,
        "Centimeters": 0.0,
        "Millimeters": 0.0
      }
    },
    {
      "Buildings": [
        " EX",
        " MC"
      ],
      "WalkingTime": "00:03:00",
      "WalkingDistance": {
        "Kilometers": 0.2,
        "Meters": 0.0,
        "Centimeters": 0.0,
        "Millimeters": 0.0
      },
      "CyclingTime": "00:00:00",
      "CyclingDistance": {
        "Kilometers": 0.0,
        "Meters": 0.0,
        "Centimeters": 0.0,
        "Millimeters": 0.0
      },
      "DrivingTime": "00:00:00",
      "DrivingDistance": {
        "Kilometers": 0.0,
        "Meters": 0.0,
        "Centimeters": 0.0,
        "Millimeters": 0.0
      }
    },
    {
      "Buildings": [
        " EX",
        " MS"
      ],
      "WalkingTime": "00:06:00",
      "WalkingDistance": {
        "Kilometers": 0.5,
        "Meters": 0.0,
        "Centimeters": 0.0,
        "Millimeters": 0.0
      },
      "CyclingTime": "00:00:00",
      "CyclingDistance": {
        "Kilometers": 0.0,
        "Meters": 0.0,
        "Centimeters": 0.0,
        "Millimeters": 0.0
      },
      "DrivingTime": "00:00:00",
      "DrivingDistance": {
        "Kilometers": 0.0,
        "Meters": 0.0,
        "Centimeters": 0.0,
        "Millimeters": 0.0
      }
    },
    {
      "Buildings": [
        " EX",
        " MH"
      ],
      "WalkingTime": "00:13:00",
      "WalkingDistance": {
        "Kilometers": 1.0,
        "Meters": 0.0,
        "Centimeters": 0.0,
        "Millimeters": 0.0
      },
      "CyclingTime": "00:00:00",
      "CyclingDistance": {
        "Kilometers": 0.0,
        "Meters": 0.0,
        "Centimeters": 0.0,
        "Millimeters": 0.0
      },
      "DrivingTime": "00:00:00",
      "DrivingDistance": {
        "Kilometers": 0.0,
        "Meters": 0.0,
        "Centimeters": 0.0,
        "Millimeters": 0.0
      }
    },
    {
      "Buildings": [
        " EX",
        " MO"
      ],
      "WalkingTime": "00:10:00",
      "WalkingDistance": {
        "Kilometers": 0.8,
        "Meters": 0.0,
        "Centimeters": 0.0,
        "Millimeters": 0.0
      },
      "CyclingTime": "00:00:00",
      "CyclingDistance": {
        "Kilometers": 0.0,
        "Meters": 0.0,
        "Centimeters": 0.0,
        "Millimeters": 0.0
      },
      "DrivingTime": "00:00:00",
      "DrivingDistance": {
        "Kilometers": 0.0,
        "Meters": 0.0,
        "Centimeters": 0.0,
        "Millimeters": 0.0
      }
    },
    {
      "Buildings": [
        " EX",
        " MU"
      ],
      "WalkingTime": "00:14:00",
      "WalkingDistance": {
        "Kilometers": 1.1,
        "Meters": 0.0,
        "Centimeters": 0.0,
        "Millimeters": 0.0
      },
      "CyclingTime": "00:00:00",
      "CyclingDistance": {
        "Kilometers": 0.0,
        "Meters": 0.0,
        "Centimeters": 0.0,
        "Millimeters": 0.0
      },
      "DrivingTime": "00:00:00",
      "DrivingDistance": {
        "Kilometers": 0.0,
        "Meters": 0.0,
        "Centimeters": 0.0,
        "Millimeters": 0.0
      }
    },
    {
      "Buildings": [
        " EX",
        " MK"
      ],
      "WalkingTime": "00:17:00",
      "WalkingDistance": {
        "Kilometers": 1.4,
        "Meters": 0.0,
        "Centimeters": 0.0,
        "Millimeters": 0.0
      },
      "CyclingTime": "00:00:00",
      "CyclingDistance": {
        "Kilometers": 0.0,
        "Meters": 0.0,
        "Centimeters": 0.0,
        "Millimeters": 0.0
      },
      "DrivingTime": "00:00:00",
      "DrivingDistance": {
        "Kilometers": 0.0,
        "Meters": 0.0,
        "Centimeters": 0.0,
        "Millimeters": 0.0
      }
    },
    {
      "Buildings": [
        " EX",
        " MU"
      ],
      "WalkingTime": "00:12:00",
      "WalkingDistance": {
        "Kilometers": 1.0,
        "Meters": 0.0,
        "Centimeters": 0.0,
        "Millimeters": 0.0
      },
      "CyclingTime": "00:00:00",
      "CyclingDistance": {
        "Kilometers": 0.0,
        "Meters": 0.0,
        "Centimeters": 0.0,
        "Millimeters": 0.0
      },
      "DrivingTime": "00:00:00",
      "DrivingDistance": {
        "Kilometers": 0.0,
        "Meters": 0.0,
        "Centimeters": 0.0,
        "Millimeters": 0.0
      }
    },
    {
      "Buildings": [
        " EX",
        " AH"
      ],
      "WalkingTime": "00:12:00",
      "WalkingDistance": {
        "Kilometers": 0.9,
        "Meters": 0.0,
        "Centimeters": 0.0,
        "Millimeters": 0.0
      },
      "CyclingTime": "00:00:00",
      "CyclingDistance": {
        "Kilometers": 0.0,
        "Meters": 0.0,
        "Centimeters": 0.0,
        "Millimeters": 0.0
      },
      "DrivingTime": "00:00:00",
      "DrivingDistance": {
        "Kilometers": 0.0,
        "Meters": 0.0,
        "Centimeters": 0.0,
        "Millimeters": 0.0
      }
    },
    {
      "Buildings": [
        " EX",
        " NR"
      ],
      "WalkingTime": "00:13:00",
      "WalkingDistance": {
        "Kilometers": 1.0,
        "Meters": 0.0,
        "Centimeters": 0.0,
        "Millimeters": 0.0
      },
      "CyclingTime": "00:00:00",
      "CyclingDistance": {
        "Kilometers": 0.0,
        "Meters": 0.0,
        "Centimeters": 0.0,
        "Millimeters": 0.0
      },
      "DrivingTime": "00:00:00",
      "DrivingDistance": {
        "Kilometers": 0.0,
        "Meters": 0.0,
        "Centimeters": 0.0,
        "Millimeters": 0.0
      }
    },
    {
      "Buildings": [
        " EX",
        " VI"
      ],
      "WalkingTime": "00:06:00",
      "WalkingDistance": {
        "Kilometers": 0.5,
        "Meters": 0.0,
        "Centimeters": 0.0,
        "Millimeters": 0.0
      },
      "CyclingTime": "00:00:00",
      "CyclingDistance": {
        "Kilometers": 0.0,
        "Meters": 0.0,
        "Centimeters": 0.0,
        "Millimeters": 0.0
      },
      "DrivingTime": "00:00:00",
      "DrivingDistance": {
        "Kilometers": 0.0,
        "Meters": 0.0,
        "Centimeters": 0.0,
        "Millimeters": 0.0
      }
    },
    {
      "Buildings": [
        " EX",
        " NF"
      ],
      "WalkingTime": "00:14:00",
      "WalkingDistance": {
        "Kilometers": 1.1,
        "Meters": 0.0,
        "Centimeters": 0.0,
        "Millimeters": 0.0
      },
      "CyclingTime": "00:00:00",
      "CyclingDistance": {
        "Kilometers": 0.0,
        "Meters": 0.0,
        "Centimeters": 0.0,
        "Millimeters": 0.0
      },
      "DrivingTime": "00:00:00",
      "DrivingDistance": {
        "Kilometers": 0.0,
        "Meters": 0.0,
        "Centimeters": 0.0,
        "Millimeters": 0.0
      }
    },
    {
      "Buildings": [
        " EX",
        " OH"
      ],
      "WalkingTime": "00:14:00",
      "WalkingDistance": {
        "Kilometers": 1.1,
        "Meters": 0.0,
        "Centimeters": 0.0,
        "Millimeters": 0.0
      },
      "CyclingTime": "00:00:00",
      "CyclingDistance": {
        "Kilometers": 0.0,
        "Meters": 0.0,
        "Centimeters": 0.0,
        "Millimeters": 0.0
      },
      "DrivingTime": "00:00:00",
      "DrivingDistance": {
        "Kilometers": 0.0,
        "Meters": 0.0,
        "Centimeters": 0.0,
        "Millimeters": 0.0
      }
    },
    {
      "Buildings": [
        " EX",
        " OA"
      ],
      "WalkingTime": "00:01:00",
      "WalkingDistance": {
        "Kilometers": 0.0,
        "Meters": 24.0,
        "Centimeters": 0.0,
        "Millimeters": 0.0
      },
      "CyclingTime": "00:00:00",
      "CyclingDistance": {
        "Kilometers": 0.0,
        "Meters": 0.0,
        "Centimeters": 0.0,
        "Millimeters": 0.0
      },
      "DrivingTime": "00:00:00",
      "DrivingDistance": {
        "Kilometers": 0.0,
        "Meters": 0.0,
        "Centimeters": 0.0,
        "Millimeters": 0.0
      }
    },
    {
      "Buildings": [
        " EX",
        " OI"
      ],
      "WalkingTime": "00:17:00",
      "WalkingDistance": {
        "Kilometers": 1.3,
        "Meters": 0.0,
        "Centimeters": 0.0,
        "Millimeters": 0.0
      },
      "CyclingTime": "00:00:00",
      "CyclingDistance": {
        "Kilometers": 0.0,
        "Meters": 0.0,
        "Centimeters": 0.0,
        "Millimeters": 0.0
      },
      "DrivingTime": "00:00:00",
      "DrivingDistance": {
        "Kilometers": 0.0,
        "Meters": 0.0,
        "Centimeters": 0.0,
        "Millimeters": 0.0
      }
    },
    {
      "Buildings": [
        " EX",
        " PH"
      ],
      "WalkingTime": "00:15:00",
      "WalkingDistance": {
        "Kilometers": 1.1,
        "Meters": 0.0,
        "Centimeters": 0.0,
        "Millimeters": 0.0
      },
      "CyclingTime": "00:00:00",
      "CyclingDistance": {
        "Kilometers": 0.0,
        "Meters": 0.0,
        "Centimeters": 0.0,
        "Millimeters": 0.0
      },
      "DrivingTime": "00:00:00",
      "DrivingDistance": {
        "Kilometers": 0.0,
        "Meters": 0.0,
        "Centimeters": 0.0,
        "Millimeters": 0.0
      }
    },
    {
      "Buildings": [
        " EX",
        " PI"
      ],
      "WalkingTime": "00:13:00",
      "WalkingDistance": {
        "Kilometers": 1.0,
        "Meters": 0.0,
        "Centimeters": 0.0,
        "Millimeters": 0.0
      },
      "CyclingTime": "00:00:00",
      "CyclingDistance": {
        "Kilometers": 0.0,
        "Meters": 0.0,
        "Centimeters": 0.0,
        "Millimeters": 0.0
      },
      "DrivingTime": "00:00:00",
      "DrivingDistance": {
        "Kilometers": 0.0,
        "Meters": 0.0,
        "Centimeters": 0.0,
        "Millimeters": 0.0
      }
    },
    {
      "Buildings": [
        " EX",
        " ME"
      ],
      "WalkingTime": "00:11:00",
      "WalkingDistance": {
        "Kilometers": 0.8,
        "Meters": 0.0,
        "Centimeters": 0.0,
        "Millimeters": 0.0
      },
      "CyclingTime": "00:00:00",
      "CyclingDistance": {
        "Kilometers": 0.0,
        "Meters": 0.0,
        "Centimeters": 0.0,
        "Millimeters": 0.0
      },
      "DrivingTime": "00:00:00",
      "DrivingDistance": {
        "Kilometers": 0.0,
        "Meters": 0.0,
        "Centimeters": 0.0,
        "Millimeters": 0.0
      }
    },
    {
      "Buildings": [
        " EX",
        " XQ"
      ],
      "WalkingTime": "00:12:00",
      "WalkingDistance": {
        "Kilometers": 0.9,
        "Meters": 0.0,
        "Centimeters": 0.0,
        "Millimeters": 0.0
      },
      "CyclingTime": "00:00:00",
      "CyclingDistance": {
        "Kilometers": 0.0,
        "Meters": 0.0,
        "Centimeters": 0.0,
        "Millimeters": 0.0
      },
      "DrivingTime": "00:00:00",
      "DrivingDistance": {
        "Kilometers": 0.0,
        "Meters": 0.0,
        "Centimeters": 0.0,
        "Millimeters": 0.0
      }
    },
    {
      "Buildings": [
        " EX",
        " ML"
      ],
      "WalkingTime": "00:11:00",
      "WalkingDistance": {
        "Kilometers": 0.8,
        "Meters": 0.0,
        "Centimeters": 0.0,
        "Millimeters": 0.0
      },
      "CyclingTime": "00:00:00",
      "CyclingDistance": {
        "Kilometers": 0.0,
        "Meters": 0.0,
        "Centimeters": 0.0,
        "Millimeters": 0.0
      },
      "DrivingTime": "00:00:00",
      "DrivingDistance": {
        "Kilometers": 0.0,
        "Meters": 0.0,
        "Centimeters": 0.0,
        "Millimeters": 0.0
      }
    },
    {
      "Buildings": [
        " EX",
        " PL"
      ],
      "WalkingTime": "00:15:00",
      "WalkingDistance": {
        "Kilometers": 1.2,
        "Meters": 0.0,
        "Centimeters": 0.0,
        "Millimeters": 0.0
      },
      "CyclingTime": "00:00:00",
      "CyclingDistance": {
        "Kilometers": 0.0,
        "Meters": 0.0,
        "Centimeters": 0.0,
        "Millimeters": 0.0
      },
      "DrivingTime": "00:00:00",
      "DrivingDistance": {
        "Kilometers": 0.0,
        "Meters": 0.0,
        "Centimeters": 0.0,
        "Millimeters": 0.0
      }
    },
    {
      "Buildings": [
        " EX",
        " RW"
      ],
      "WalkingTime": "00:12:00",
      "WalkingDistance": {
        "Kilometers": 0.9,
        "Meters": 0.0,
        "Centimeters": 0.0,
        "Millimeters": 0.0
      },
      "CyclingTime": "00:00:00",
      "CyclingDistance": {
        "Kilometers": 0.0,
        "Meters": 0.0,
        "Centimeters": 0.0,
        "Millimeters": 0.0
      },
      "DrivingTime": "00:00:00",
      "DrivingDistance": {
        "Kilometers": 0.0,
        "Meters": 0.0,
        "Centimeters": 0.0,
        "Millimeters": 0.0
      }
    },
    {
      "Buildings": [
        " EX",
        " RG"
      ],
      "WalkingTime": "00:11:00",
      "WalkingDistance": {
        "Kilometers": 0.8,
        "Meters": 0.0,
        "Centimeters": 0.0,
        "Millimeters": 0.0
      },
      "CyclingTime": "00:00:00",
      "CyclingDistance": {
        "Kilometers": 0.0,
        "Meters": 0.0,
        "Centimeters": 0.0,
        "Millimeters": 0.0
      },
      "DrivingTime": "00:00:00",
      "DrivingDistance": {
        "Kilometers": 0.0,
        "Meters": 0.0,
        "Centimeters": 0.0,
        "Millimeters": 0.0
      }
    },
    {
      "Buildings": [
        " EX",
        " RU"
      ],
      "WalkingTime": "00:08:00",
      "WalkingDistance": {
        "Kilometers": 0.6,
        "Meters": 0.0,
        "Centimeters": 0.0,
        "Millimeters": 0.0
      },
      "CyclingTime": "00:00:00",
      "CyclingDistance": {
        "Kilometers": 0.0,
        "Meters": 0.0,
        "Centimeters": 0.0,
        "Millimeters": 0.0
      },
      "DrivingTime": "00:00:00",
      "DrivingDistance": {
        "Kilometers": 0.0,
        "Meters": 0.0,
        "Centimeters": 0.0,
        "Millimeters": 0.0
      }
    },
    {
      "Buildings": [
        " EX",
        " RS"
      ],
      "WalkingTime": "00:02:00",
      "WalkingDistance": {
        "Kilometers": 0.2,
        "Meters": 0.0,
        "Centimeters": 0.0,
        "Millimeters": 0.0
      },
      "CyclingTime": "00:00:00",
      "CyclingDistance": {
        "Kilometers": 0.0,
        "Meters": 0.0,
        "Centimeters": 0.0,
        "Millimeters": 0.0
      },
      "DrivingTime": "00:00:00",
      "DrivingDistance": {
        "Kilometers": 0.0,
        "Meters": 0.0,
        "Centimeters": 0.0,
        "Millimeters": 0.0
      }
    },
    {
      "Buildings": [
        " EX",
        " RT"
      ],
      "WalkingTime": "00:14:00",
      "WalkingDistance": {
        "Kilometers": 1.1,
        "Meters": 0.0,
        "Centimeters": 0.0,
        "Millimeters": 0.0
      },
      "CyclingTime": "00:00:00",
      "CyclingDistance": {
        "Kilometers": 0.0,
        "Meters": 0.0,
        "Centimeters": 0.0,
        "Millimeters": 0.0
      },
      "DrivingTime": "00:00:00",
      "DrivingDistance": {
        "Kilometers": 0.0,
        "Meters": 0.0,
        "Centimeters": 0.0,
        "Millimeters": 0.0
      }
    },
    {
      "Buildings": [
        " EX",
        " RJ"
      ],
      "WalkingTime": "00:17:00",
      "WalkingDistance": {
        "Kilometers": 1.3,
        "Meters": 0.0,
        "Centimeters": 0.0,
        "Millimeters": 0.0
      },
      "CyclingTime": "00:00:00",
      "CyclingDistance": {
        "Kilometers": 0.0,
        "Meters": 0.0,
        "Centimeters": 0.0,
        "Millimeters": 0.0
      },
      "DrivingTime": "00:00:00",
      "DrivingDistance": {
        "Kilometers": 0.0,
        "Meters": 0.0,
        "Centimeters": 0.0,
        "Millimeters": 0.0
      }
    },
    {
      "Buildings": [
        " EX",
        " SR"
      ],
      "WalkingTime": "00:15:00",
      "WalkingDistance": {
        "Kilometers": 1.1,
        "Meters": 0.0,
        "Centimeters": 0.0,
        "Millimeters": 0.0
      },
      "CyclingTime": "00:00:00",
      "CyclingDistance": {
        "Kilometers": 0.0,
        "Meters": 0.0,
        "Centimeters": 0.0,
        "Millimeters": 0.0
      },
      "DrivingTime": "00:00:00",
      "DrivingDistance": {
        "Kilometers": 0.0,
        "Meters": 0.0,
        "Centimeters": 0.0,
        "Millimeters": 0.0
      }
    },
    {
      "Buildings": [
        " EX",
        " SF"
      ],
      "WalkingTime": "00:03:00",
      "WalkingDistance": {
        "Kilometers": 0.3,
        "Meters": 0.0,
        "Centimeters": 0.0,
        "Millimeters": 0.0
      },
      "CyclingTime": "00:00:00",
      "CyclingDistance": {
        "Kilometers": 0.0,
        "Meters": 0.0,
        "Centimeters": 0.0,
        "Millimeters": 0.0
      },
      "DrivingTime": "00:00:00",
      "DrivingDistance": {
        "Kilometers": 0.0,
        "Meters": 0.0,
        "Centimeters": 0.0,
        "Millimeters": 0.0
      }
    },
    {
      "Buildings": [
        " EX",
        " CS"
      ],
      "WalkingTime": "00:16:00",
      "WalkingDistance": {
        "Kilometers": 1.2,
        "Meters": 0.0,
        "Centimeters": 0.0,
        "Millimeters": 0.0
      },
      "CyclingTime": "00:00:00",
      "CyclingDistance": {
        "Kilometers": 0.0,
        "Meters": 0.0,
        "Centimeters": 0.0,
        "Millimeters": 0.0
      },
      "DrivingTime": "00:00:00",
      "DrivingDistance": {
        "Kilometers": 0.0,
        "Meters": 0.0,
        "Centimeters": 0.0,
        "Millimeters": 0.0
      }
    },
    {
      "Buildings": [
        " EX",
        " GS"
      ],
      "WalkingTime": "00:09:00",
      "WalkingDistance": {
        "Kilometers": 0.7,
        "Meters": 0.0,
        "Centimeters": 0.0,
        "Millimeters": 0.0
      },
      "CyclingTime": "00:00:00",
      "CyclingDistance": {
        "Kilometers": 0.0,
        "Meters": 0.0,
        "Centimeters": 0.0,
        "Millimeters": 0.0
      },
      "DrivingTime": "00:00:00",
      "DrivingDistance": {
        "Kilometers": 0.0,
        "Meters": 0.0,
        "Centimeters": 0.0,
        "Millimeters": 0.0
      }
    },
    {
      "Buildings": [
        " EX",
        " SS"
      ],
      "WalkingTime": "00:10:00",
      "WalkingDistance": {
        "Kilometers": 0.8,
        "Meters": 0.0,
        "Centimeters": 0.0,
        "Millimeters": 0.0
      },
      "CyclingTime": "00:00:00",
      "CyclingDistance": {
        "Kilometers": 0.0,
        "Meters": 0.0,
        "Centimeters": 0.0,
        "Millimeters": 0.0
      },
      "DrivingTime": "00:00:00",
      "DrivingDistance": {
        "Kilometers": 0.0,
        "Meters": 0.0,
        "Centimeters": 0.0,
        "Millimeters": 0.0
      }
    },
    {
      "Buildings": [
        " EX",
        " SI"
      ],
      "WalkingTime": "00:09:00",
      "WalkingDistance": {
        "Kilometers": 0.7,
        "Meters": 0.0,
        "Centimeters": 0.0,
        "Millimeters": 0.0
      },
      "CyclingTime": "00:00:00",
      "CyclingDistance": {
        "Kilometers": 0.0,
        "Meters": 0.0,
        "Centimeters": 0.0,
        "Millimeters": 0.0
      },
      "DrivingTime": "00:00:00",
      "DrivingDistance": {
        "Kilometers": 0.0,
        "Meters": 0.0,
        "Centimeters": 0.0,
        "Millimeters": 0.0
      }
    },
    {
      "Buildings": [
        " EX",
        " SD"
      ],
      "WalkingTime": "00:09:00",
      "WalkingDistance": {
        "Kilometers": 0.7,
        "Meters": 0.0,
        "Centimeters": 0.0,
        "Millimeters": 0.0
      },
      "CyclingTime": "00:00:00",
      "CyclingDistance": {
        "Kilometers": 0.0,
        "Meters": 0.0,
        "Centimeters": 0.0,
        "Millimeters": 0.0
      },
      "DrivingTime": "00:00:00",
      "DrivingDistance": {
        "Kilometers": 0.0,
        "Meters": 0.0,
        "Centimeters": 0.0,
        "Millimeters": 0.0
      }
    },
    {
      "Buildings": [
        " EX",
        " TR"
      ],
      "WalkingTime": "00:09:00",
      "WalkingDistance": {
        "Kilometers": 0.7,
        "Meters": 0.0,
        "Centimeters": 0.0,
        "Millimeters": 0.0
      },
      "CyclingTime": "00:00:00",
      "CyclingDistance": {
        "Kilometers": 0.0,
        "Meters": 0.0,
        "Centimeters": 0.0,
        "Millimeters": 0.0
      },
      "DrivingTime": "00:00:00",
      "DrivingDistance": {
        "Kilometers": 0.0,
        "Meters": 0.0,
        "Centimeters": 0.0,
        "Millimeters": 0.0
      }
    },
    {
      "Buildings": [
        " EX",
        " TT"
      ],
      "WalkingTime": "00:08:00",
      "WalkingDistance": {
        "Kilometers": 0.6,
        "Meters": 0.0,
        "Centimeters": 0.0,
        "Millimeters": 0.0
      },
      "CyclingTime": "00:00:00",
      "CyclingDistance": {
        "Kilometers": 0.0,
        "Meters": 0.0,
        "Centimeters": 0.0,
        "Millimeters": 0.0
      },
      "DrivingTime": "00:00:00",
      "DrivingDistance": {
        "Kilometers": 0.0,
        "Meters": 0.0,
        "Centimeters": 0.0,
        "Millimeters": 0.0
      }
    },
    {
      "Buildings": [
        " EX",
        " SA"
      ],
      "WalkingTime": "00:19:00",
      "WalkingDistance": {
        "Kilometers": 1.5,
        "Meters": 0.0,
        "Centimeters": 0.0,
        "Millimeters": 0.0
      },
      "CyclingTime": "00:00:00",
      "CyclingDistance": {
        "Kilometers": 0.0,
        "Meters": 0.0,
        "Centimeters": 0.0,
        "Millimeters": 0.0
      },
      "DrivingTime": "00:00:00",
      "DrivingDistance": {
        "Kilometers": 0.0,
        "Meters": 0.0,
        "Centimeters": 0.0,
        "Millimeters": 0.0
      }
    },
    {
      "Buildings": [
        " EX",
        " XG"
      ],
      "WalkingTime": "00:17:00",
      "WalkingDistance": {
        "Kilometers": 1.3,
        "Meters": 0.0,
        "Centimeters": 0.0,
        "Millimeters": 0.0
      },
      "CyclingTime": "00:00:00",
      "CyclingDistance": {
        "Kilometers": 0.0,
        "Meters": 0.0,
        "Centimeters": 0.0,
        "Millimeters": 0.0
      },
      "DrivingTime": "00:00:00",
      "DrivingDistance": {
        "Kilometers": 0.0,
        "Meters": 0.0,
        "Centimeters": 0.0,
        "Millimeters": 0.0
      }
    },
    {
      "Buildings": [
        " EX",
        " IA"
      ],
      "WalkingTime": "00:18:00",
      "WalkingDistance": {
        "Kilometers": 1.4,
        "Meters": 0.0,
        "Centimeters": 0.0,
        "Millimeters": 0.0
      },
      "CyclingTime": "00:00:00",
      "CyclingDistance": {
        "Kilometers": 0.0,
        "Meters": 0.0,
        "Centimeters": 0.0,
        "Millimeters": 0.0
      },
      "DrivingTime": "00:00:00",
      "DrivingDistance": {
        "Kilometers": 0.0,
        "Meters": 0.0,
        "Centimeters": 0.0,
        "Millimeters": 0.0
      }
    },
    {
      "Buildings": [
        " EX",
        " FA"
      ],
      "WalkingTime": "00:19:00",
      "WalkingDistance": {
        "Kilometers": 1.4,
        "Meters": 0.0,
        "Centimeters": 0.0,
        "Millimeters": 0.0
      },
      "CyclingTime": "00:00:00",
      "CyclingDistance": {
        "Kilometers": 0.0,
        "Meters": 0.0,
        "Centimeters": 0.0,
        "Millimeters": 0.0
      },
      "DrivingTime": "00:00:00",
      "DrivingDistance": {
        "Kilometers": 0.0,
        "Meters": 0.0,
        "Centimeters": 0.0,
        "Millimeters": 0.0
      }
    },
    {
      "Buildings": [
        " EX",
        " CD"
      ],
      "WalkingTime": "00:25:00",
      "WalkingDistance": {
        "Kilometers": 1.9,
        "Meters": 0.0,
        "Centimeters": 0.0,
        "Millimeters": 0.0
      },
      "CyclingTime": "00:00:00",
      "CyclingDistance": {
        "Kilometers": 0.0,
        "Meters": 0.0,
        "Centimeters": 0.0,
        "Millimeters": 0.0
      },
      "DrivingTime": "00:00:00",
      "DrivingDistance": {
        "Kilometers": 0.0,
        "Meters": 0.0,
        "Centimeters": 0.0,
        "Millimeters": 0.0
      }
    },
    {
      "Buildings": [
        " EX",
        " BS"
      ],
      "WalkingTime": "00:14:00",
      "WalkingDistance": {
        "Kilometers": 1.1,
        "Meters": 0.0,
        "Centimeters": 0.0,
        "Millimeters": 0.0
      },
      "CyclingTime": "00:00:00",
      "CyclingDistance": {
        "Kilometers": 0.0,
        "Meters": 0.0,
        "Centimeters": 0.0,
        "Millimeters": 0.0
      },
      "DrivingTime": "00:00:00",
      "DrivingDistance": {
        "Kilometers": 0.0,
        "Meters": 0.0,
        "Centimeters": 0.0,
        "Millimeters": 0.0
      }
    },
    {
      "Buildings": [
        " EX",
        " IR"
      ],
      "WalkingTime": "00:15:00",
      "WalkingDistance": {
        "Kilometers": 1.2,
        "Meters": 0.0,
        "Centimeters": 0.0,
        "Millimeters": 0.0
      },
      "CyclingTime": "00:00:00",
      "CyclingDistance": {
        "Kilometers": 0.0,
        "Meters": 0.0,
        "Centimeters": 0.0,
        "Millimeters": 0.0
      },
      "DrivingTime": "00:00:00",
      "DrivingDistance": {
        "Kilometers": 0.0,
        "Meters": 0.0,
        "Centimeters": 0.0,
        "Millimeters": 0.0
      }
    },
    {
      "Buildings": [
        " EX",
        " CO"
      ],
      "WalkingTime": "00:14:00",
      "WalkingDistance": {
        "Kilometers": 1.1,
        "Meters": 0.0,
        "Centimeters": 0.0,
        "Millimeters": 0.0
      },
      "CyclingTime": "00:00:00",
      "CyclingDistance": {
        "Kilometers": 0.0,
        "Meters": 0.0,
        "Centimeters": 0.0,
        "Millimeters": 0.0
      },
      "DrivingTime": "00:00:00",
      "DrivingDistance": {
        "Kilometers": 0.0,
        "Meters": 0.0,
        "Centimeters": 0.0,
        "Millimeters": 0.0
      }
    },
    {
      "Buildings": [
        " EX",
        " PG"
      ],
      "WalkingTime": "00:07:00",
      "WalkingDistance": {
        "Kilometers": 0.5,
        "Meters": 0.0,
        "Centimeters": 0.0,
        "Millimeters": 0.0
      },
      "CyclingTime": "00:00:00",
      "CyclingDistance": {
        "Kilometers": 0.0,
        "Meters": 0.0,
        "Centimeters": 0.0,
        "Millimeters": 0.0
      },
      "DrivingTime": "00:00:00",
      "DrivingDistance": {
        "Kilometers": 0.0,
        "Meters": 0.0,
        "Centimeters": 0.0,
        "Millimeters": 0.0
      }
    },
    {
      "Buildings": [
        " EX",
        " SG"
      ],
      "WalkingTime": "00:05:00",
      "WalkingDistance": {
        "Kilometers": 0.4,
        "Meters": 0.0,
        "Centimeters": 0.0,
        "Millimeters": 0.0
      },
      "CyclingTime": "00:00:00",
      "CyclingDistance": {
        "Kilometers": 0.0,
        "Meters": 0.0,
        "Centimeters": 0.0,
        "Millimeters": 0.0
      },
      "DrivingTime": "00:00:00",
      "DrivingDistance": {
        "Kilometers": 0.0,
        "Meters": 0.0,
        "Centimeters": 0.0,
        "Millimeters": 0.0
      }
    },
    {
      "Buildings": [
        " EX",
        " WA"
      ],
      "WalkingTime": "00:16:00",
      "WalkingDistance": {
        "Kilometers": 1.2,
        "Meters": 0.0,
        "Centimeters": 0.0,
        "Millimeters": 0.0
      },
      "CyclingTime": "00:00:00",
      "CyclingDistance": {
        "Kilometers": 0.0,
        "Meters": 0.0,
        "Centimeters": 0.0,
        "Millimeters": 0.0
      },
      "DrivingTime": "00:00:00",
      "DrivingDistance": {
        "Kilometers": 0.0,
        "Meters": 0.0,
        "Centimeters": 0.0,
        "Millimeters": 0.0
      }
    },
    {
      "Buildings": [
        " EX",
        " HI"
      ],
      "WalkingTime": "00:14:00",
      "WalkingDistance": {
        "Kilometers": 1.1,
        "Meters": 0.0,
        "Centimeters": 0.0,
        "Millimeters": 0.0
      },
      "CyclingTime": "00:00:00",
      "CyclingDistance": {
        "Kilometers": 0.0,
        "Meters": 0.0,
        "Centimeters": 0.0,
        "Millimeters": 0.0
      },
      "DrivingTime": "00:00:00",
      "DrivingDistance": {
        "Kilometers": 0.0,
        "Meters": 0.0,
        "Centimeters": 0.0,
        "Millimeters": 0.0
      }
    },
    {
      "Buildings": [
        " EX",
        " SN"
      ],
      "WalkingTime": "00:18:00",
      "WalkingDistance": {
        "Kilometers": 1.4,
        "Meters": 0.0,
        "Centimeters": 0.0,
        "Millimeters": 0.0
      },
      "CyclingTime": "00:00:00",
      "CyclingDistance": {
        "Kilometers": 0.0,
        "Meters": 0.0,
        "Centimeters": 0.0,
        "Millimeters": 0.0
      },
      "DrivingTime": "00:00:00",
      "DrivingDistance": {
        "Kilometers": 0.0,
        "Meters": 0.0,
        "Centimeters": 0.0,
        "Millimeters": 0.0
      }
    },
    {
      "Buildings": [
        " EX",
        " EP"
      ],
      "WalkingTime": "00:02:00",
      "WalkingDistance": {
        "Kilometers": 0.2,
        "Meters": 0.0,
        "Centimeters": 0.0,
        "Millimeters": 0.0
      },
      "CyclingTime": "00:00:00",
      "CyclingDistance": {
        "Kilometers": 0.0,
        "Meters": 0.0,
        "Centimeters": 0.0,
        "Millimeters": 0.0
      },
      "DrivingTime": "00:00:00",
      "DrivingDistance": {
        "Kilometers": 0.0,
        "Meters": 0.0,
        "Centimeters": 0.0,
        "Millimeters": 0.0
      }
    },
    {
      "Buildings": [
        " EX",
        " SV"
      ],
      "WalkingTime": "00:13:00",
      "WalkingDistance": {
        "Kilometers": 1.0,
        "Meters": 0.0,
        "Centimeters": 0.0,
        "Millimeters": 0.0
      },
      "CyclingTime": "00:00:00",
      "CyclingDistance": {
        "Kilometers": 0.0,
        "Meters": 0.0,
        "Centimeters": 0.0,
        "Millimeters": 0.0
      },
      "DrivingTime": "00:00:00",
      "DrivingDistance": {
        "Kilometers": 0.0,
        "Meters": 0.0,
        "Centimeters": 0.0,
        "Millimeters": 0.0
      }
    },
    {
      "Buildings": [
        " EX",
        " SU"
      ],
      "WalkingTime": "00:16:00",
      "WalkingDistance": {
        "Kilometers": 1.2,
        "Meters": 0.0,
        "Centimeters": 0.0,
        "Millimeters": 0.0
      },
      "CyclingTime": "00:00:00",
      "CyclingDistance": {
        "Kilometers": 0.0,
        "Meters": 0.0,
        "Centimeters": 0.0,
        "Millimeters": 0.0
      },
      "DrivingTime": "00:00:00",
      "DrivingDistance": {
        "Kilometers": 0.0,
        "Meters": 0.0,
        "Centimeters": 0.0,
        "Millimeters": 0.0
      }
    },
    {
      "Buildings": [
        " EX",
        " SC"
      ],
      "WalkingTime": "00:15:00",
      "WalkingDistance": {
        "Kilometers": 1.2,
        "Meters": 0.0,
        "Centimeters": 0.0,
        "Millimeters": 0.0
      },
      "CyclingTime": "00:00:00",
      "CyclingDistance": {
        "Kilometers": 0.0,
        "Meters": 0.0,
        "Centimeters": 0.0,
        "Millimeters": 0.0
      },
      "DrivingTime": "00:00:00",
      "DrivingDistance": {
        "Kilometers": 0.0,
        "Meters": 0.0,
        "Centimeters": 0.0,
        "Millimeters": 0.0
      }
    },
    {
      "Buildings": [
        " EX",
        " TF"
      ],
      "WalkingTime": "00:13:00",
      "WalkingDistance": {
        "Kilometers": 1.0,
        "Meters": 0.0,
        "Centimeters": 0.0,
        "Millimeters": 0.0
      },
      "CyclingTime": "00:00:00",
      "CyclingDistance": {
        "Kilometers": 0.0,
        "Meters": 0.0,
        "Centimeters": 0.0,
        "Millimeters": 0.0
      },
      "DrivingTime": "00:00:00",
      "DrivingDistance": {
        "Kilometers": 0.0,
        "Meters": 0.0,
        "Centimeters": 0.0,
        "Millimeters": 0.0
      }
    },
    {
      "Buildings": [
        " EX",
        " DC"
      ],
      "WalkingTime": "00:02:00",
      "WalkingDistance": {
        "Kilometers": 0.2,
        "Meters": 0.0,
        "Centimeters": 0.0,
        "Millimeters": 0.0
      },
      "CyclingTime": "00:00:00",
      "CyclingDistance": {
        "Kilometers": 0.0,
        "Meters": 0.0,
        "Centimeters": 0.0,
        "Millimeters": 0.0
      },
      "DrivingTime": "00:00:00",
      "DrivingDistance": {
        "Kilometers": 0.0,
        "Meters": 0.0,
        "Centimeters": 0.0,
        "Millimeters": 0.0
      }
    },
    {
      "Buildings": [
        " EX",
        " RB"
      ],
      "WalkingTime": "00:12:00",
      "WalkingDistance": {
        "Kilometers": 0.9,
        "Meters": 0.0,
        "Centimeters": 0.0,
        "Millimeters": 0.0
      },
      "CyclingTime": "00:00:00",
      "CyclingDistance": {
        "Kilometers": 0.0,
        "Meters": 0.0,
        "Centimeters": 0.0,
        "Millimeters": 0.0
      },
      "DrivingTime": "00:00:00",
      "DrivingDistance": {
        "Kilometers": 0.0,
        "Meters": 0.0,
        "Centimeters": 0.0,
        "Millimeters": 0.0
      }
    },
    {
      "Buildings": [
        " EX",
        " TH"
      ],
      "WalkingTime": "00:12:00",
      "WalkingDistance": {
        "Kilometers": 0.9,
        "Meters": 0.0,
        "Centimeters": 0.0,
        "Millimeters": 0.0
      },
      "CyclingTime": "00:00:00",
      "CyclingDistance": {
        "Kilometers": 0.0,
        "Meters": 0.0,
        "Centimeters": 0.0,
        "Millimeters": 0.0
      },
      "DrivingTime": "00:00:00",
      "DrivingDistance": {
        "Kilometers": 0.0,
        "Meters": 0.0,
        "Centimeters": 0.0,
        "Millimeters": 0.0
      }
    },
    {
      "Buildings": [
        " EX",
        " TC"
      ],
      "WalkingTime": "00:11:00",
      "WalkingDistance": {
        "Kilometers": 0.9,
        "Meters": 0.0,
        "Centimeters": 0.0,
        "Millimeters": 0.0
      },
      "CyclingTime": "00:00:00",
      "CyclingDistance": {
        "Kilometers": 0.0,
        "Meters": 0.0,
        "Centimeters": 0.0,
        "Millimeters": 0.0
      },
      "DrivingTime": "00:00:00",
      "DrivingDistance": {
        "Kilometers": 0.0,
        "Meters": 0.0,
        "Centimeters": 0.0,
        "Millimeters": 0.0
      }
    },
    {
      "Buildings": [
        " EX",
        " KT"
      ],
      "WalkingTime": "00:18:00",
      "WalkingDistance": {
        "Kilometers": 1.4,
        "Meters": 0.0,
        "Centimeters": 0.0,
        "Millimeters": 0.0
      },
      "CyclingTime": "00:00:00",
      "CyclingDistance": {
        "Kilometers": 0.0,
        "Meters": 0.0,
        "Centimeters": 0.0,
        "Millimeters": 0.0
      },
      "DrivingTime": "00:00:00",
      "DrivingDistance": {
        "Kilometers": 0.0,
        "Meters": 0.0,
        "Centimeters": 0.0,
        "Millimeters": 0.0
      }
    },
    {
      "Buildings": [
        " EX",
        " UC"
      ],
      "WalkingTime": "00:08:00",
      "WalkingDistance": {
        "Kilometers": 0.6,
        "Meters": 0.0,
        "Centimeters": 0.0,
        "Millimeters": 0.0
      },
      "CyclingTime": "00:00:00",
      "CyclingDistance": {
        "Kilometers": 0.0,
        "Meters": 0.0,
        "Centimeters": 0.0,
        "Millimeters": 0.0
      },
      "DrivingTime": "00:00:00",
      "DrivingDistance": {
        "Kilometers": 0.0,
        "Meters": 0.0,
        "Centimeters": 0.0,
        "Millimeters": 0.0
      }
    },
    {
      "Buildings": [
        " EX",
        " UP"
      ],
      "WalkingTime": "00:11:00",
      "WalkingDistance": {
        "Kilometers": 0.8,
        "Meters": 0.0,
        "Centimeters": 0.0,
        "Millimeters": 0.0
      },
      "CyclingTime": "00:00:00",
      "CyclingDistance": {
        "Kilometers": 0.0,
        "Meters": 0.0,
        "Centimeters": 0.0,
        "Millimeters": 0.0
      },
      "DrivingTime": "00:00:00",
      "DrivingDistance": {
        "Kilometers": 0.0,
        "Meters": 0.0,
        "Centimeters": 0.0,
        "Millimeters": 0.0
      }
    },
    {
      "Buildings": [
        " EX",
        " VA"
      ],
      "WalkingTime": "00:15:00",
      "WalkingDistance": {
        "Kilometers": 1.2,
        "Meters": 0.0,
        "Centimeters": 0.0,
        "Millimeters": 0.0
      },
      "CyclingTime": "00:00:00",
      "CyclingDistance": {
        "Kilometers": 0.0,
        "Meters": 0.0,
        "Centimeters": 0.0,
        "Millimeters": 0.0
      },
      "DrivingTime": "00:00:00",
      "DrivingDistance": {
        "Kilometers": 0.0,
        "Meters": 0.0,
        "Centimeters": 0.0,
        "Millimeters": 0.0
      }
    },
    {
      "Buildings": [
        " EX",
        " VP"
      ],
      "WalkingTime": "00:15:00",
      "WalkingDistance": {
        "Kilometers": 1.2,
        "Meters": 0.0,
        "Centimeters": 0.0,
        "Millimeters": 0.0
      },
      "CyclingTime": "00:00:00",
      "CyclingDistance": {
        "Kilometers": 0.0,
        "Meters": 0.0,
        "Centimeters": 0.0,
        "Millimeters": 0.0
      },
      "DrivingTime": "00:00:00",
      "DrivingDistance": {
        "Kilometers": 0.0,
        "Meters": 0.0,
        "Centimeters": 0.0,
        "Millimeters": 0.0
      }
    },
    {
      "Buildings": [
        " EX",
        " VC"
      ],
      "WalkingTime": "00:17:00",
      "WalkingDistance": {
        "Kilometers": 1.3,
        "Meters": 0.0,
        "Centimeters": 0.0,
        "Millimeters": 0.0
      },
      "CyclingTime": "00:00:00",
      "CyclingDistance": {
        "Kilometers": 0.0,
        "Meters": 0.0,
        "Centimeters": 0.0,
        "Millimeters": 0.0
      },
      "DrivingTime": "00:00:00",
      "DrivingDistance": {
        "Kilometers": 0.0,
        "Meters": 0.0,
        "Centimeters": 0.0,
        "Millimeters": 0.0
      }
    },
    {
      "Buildings": [
        " EX",
        " WB"
      ],
      "WalkingTime": "00:03:00",
      "WalkingDistance": {
        "Kilometers": 0.3,
        "Meters": 0.0,
        "Centimeters": 0.0,
        "Millimeters": 0.0
      },
      "CyclingTime": "00:00:00",
      "CyclingDistance": {
        "Kilometers": 0.0,
        "Meters": 0.0,
        "Centimeters": 0.0,
        "Millimeters": 0.0
      },
      "DrivingTime": "00:00:00",
      "DrivingDistance": {
        "Kilometers": 0.0,
        "Meters": 0.0,
        "Centimeters": 0.0,
        "Millimeters": 0.0
      }
    },
    {
      "Buildings": [
        " EX",
        " WS"
      ],
      "WalkingTime": "00:14:00",
      "WalkingDistance": {
        "Kilometers": 1.1,
        "Meters": 0.0,
        "Centimeters": 0.0,
        "Millimeters": 0.0
      },
      "CyclingTime": "00:00:00",
      "CyclingDistance": {
        "Kilometers": 0.0,
        "Meters": 0.0,
        "Centimeters": 0.0,
        "Millimeters": 0.0
      },
      "DrivingTime": "00:00:00",
      "DrivingDistance": {
        "Kilometers": 0.0,
        "Meters": 0.0,
        "Centimeters": 0.0,
        "Millimeters": 0.0
      }
    },
    {
      "Buildings": [
        " EX",
        " JP"
      ],
      "WalkingTime": "00:11:00",
      "WalkingDistance": {
        "Kilometers": 0.9,
        "Meters": 0.0,
        "Centimeters": 0.0,
        "Millimeters": 0.0
      },
      "CyclingTime": "00:00:00",
      "CyclingDistance": {
        "Kilometers": 0.0,
        "Meters": 0.0,
        "Centimeters": 0.0,
        "Millimeters": 0.0
      },
      "DrivingTime": "00:00:00",
      "DrivingDistance": {
        "Kilometers": 0.0,
        "Meters": 0.0,
        "Centimeters": 0.0,
        "Millimeters": 0.0
      }
    },
    {
      "Buildings": [
        " EX",
        " WE"
      ],
      "WalkingTime": "00:11:00",
      "WalkingDistance": {
        "Kilometers": 0.9,
        "Meters": 0.0,
        "Centimeters": 0.0,
        "Millimeters": 0.0
      },
      "CyclingTime": "00:00:00",
      "CyclingDistance": {
        "Kilometers": 0.0,
        "Meters": 0.0,
        "Centimeters": 0.0,
        "Millimeters": 0.0
      },
      "DrivingTime": "00:00:00",
      "DrivingDistance": {
        "Kilometers": 0.0,
        "Meters": 0.0,
        "Centimeters": 0.0,
        "Millimeters": 0.0
      }
    },
    {
      "Buildings": [
        " EX",
        " WT"
      ],
      "WalkingTime": "00:11:00",
      "WalkingDistance": {
        "Kilometers": 0.9,
        "Meters": 0.0,
        "Centimeters": 0.0,
        "Millimeters": 0.0
      },
      "CyclingTime": "00:00:00",
      "CyclingDistance": {
        "Kilometers": 0.0,
        "Meters": 0.0,
        "Centimeters": 0.0,
        "Millimeters": 0.0
      },
      "DrivingTime": "00:00:00",
      "DrivingDistance": {
        "Kilometers": 0.0,
        "Meters": 0.0,
        "Centimeters": 0.0,
        "Millimeters": 0.0
      }
    },
    {
      "Buildings": [
        " EX",
        " WI"
      ],
      "WalkingTime": "00:13:00",
      "WalkingDistance": {
        "Kilometers": 1.0,
        "Meters": 0.0,
        "Centimeters": 0.0,
        "Millimeters": 0.0
      },
      "CyclingTime": "00:00:00",
      "CyclingDistance": {
        "Kilometers": 0.0,
        "Meters": 0.0,
        "Centimeters": 0.0,
        "Millimeters": 0.0
      },
      "DrivingTime": "00:00:00",
      "DrivingDistance": {
        "Kilometers": 0.0,
        "Meters": 0.0,
        "Centimeters": 0.0,
        "Millimeters": 0.0
      }
    },
    {
      "Buildings": [
        " EX",
        " WN"
      ],
      "WalkingTime": "00:15:00",
      "WalkingDistance": {
        "Kilometers": 1.1,
        "Meters": 0.0,
        "Centimeters": 0.0,
        "Millimeters": 0.0
      },
      "CyclingTime": "00:00:00",
      "CyclingDistance": {
        "Kilometers": 0.0,
        "Meters": 0.0,
        "Centimeters": 0.0,
        "Millimeters": 0.0
      },
      "DrivingTime": "00:00:00",
      "DrivingDistance": {
        "Kilometers": 0.0,
        "Meters": 0.0,
        "Centimeters": 0.0,
        "Millimeters": 0.0
      }
    },
    {
      "Buildings": [
        " EX",
        " WW"
      ],
      "WalkingTime": "00:16:00",
      "WalkingDistance": {
        "Kilometers": 1.2,
        "Meters": 0.0,
        "Centimeters": 0.0,
        "Millimeters": 0.0
      },
      "CyclingTime": "00:00:00",
      "CyclingDistance": {
        "Kilometers": 0.0,
        "Meters": 0.0,
        "Centimeters": 0.0,
        "Millimeters": 0.0
      },
      "DrivingTime": "00:00:00",
      "DrivingDistance": {
        "Kilometers": 0.0,
        "Meters": 0.0,
        "Centimeters": 0.0,
        "Millimeters": 0.0
      }
    },
    {
      "Buildings": [
        " EX",
        " WO"
      ],
      "WalkingTime": "00:17:00",
      "WalkingDistance": {
        "Kilometers": 1.3,
        "Meters": 0.0,
        "Centimeters": 0.0,
        "Millimeters": 0.0
      },
      "CyclingTime": "00:00:00",
      "CyclingDistance": {
        "Kilometers": 0.0,
        "Meters": 0.0,
        "Centimeters": 0.0,
        "Millimeters": 0.0
      },
      "DrivingTime": "00:00:00",
      "DrivingDistance": {
        "Kilometers": 0.0,
        "Meters": 0.0,
        "Centimeters": 0.0,
        "Millimeters": 0.0
      }
    },
    {
      "Buildings": [
        " EX",
        " WY"
      ],
      "WalkingTime": "00:12:00",
      "WalkingDistance": {
        "Kilometers": 0.9,
        "Meters": 0.0,
        "Centimeters": 0.0,
        "Millimeters": 0.0
      },
      "CyclingTime": "00:00:00",
      "CyclingDistance": {
        "Kilometers": 0.0,
        "Meters": 0.0,
        "Centimeters": 0.0,
        "Millimeters": 0.0
      },
      "DrivingTime": "00:00:00",
      "DrivingDistance": {
        "Kilometers": 0.0,
        "Meters": 0.0,
        "Centimeters": 0.0,
        "Millimeters": 0.0
      }
    }
  ]
}