{
  "CourseName": "CSC443H1-S",
  "Term": "S",
  "Lectures": [
    {
      "MeetingCode": "LEC0101",
      "Instructor": "—",
      "Times": [
        {
          "Day": "Monday",
          "StartTime": 14.0,
          "EndTime": 15.0,
          "FallLocation": null,
          "WinterLocation": "MP 137"
        },
        {
          "Day": "Wednesday",
          "StartTime": 14.0,
          "EndTime": 15.0,
          "FallLocation": null,
          "WinterLocation": "MP 137"
        },
        {
          "Day": "Friday",
          "StartTime": 14.0,
          "EndTime": 15.0,
          "FallLocation": null,
          "WinterLocation": "MP 137"
        }
      ]
    },
    {
      "MeetingCode": "LEC2001",
      "Instructor": "—",
      "Times": [
        {
          "Day": "Monday",
          "StartTime": 14.0,
          "EndTime": 15.0,
          "FallLocation": null,
          "WinterLocation": "MP 137"
        },
        {
          "Day": "Wednesday",
          "StartTime": 14.0,
          "EndTime": 15.0,
          "FallLocation": null,
          "WinterLocation": "MP 137"
        },
        {
          "Day": "Friday",
          "StartTime": 14.0,
          "EndTime": 15.0,
          "FallLocation": null,
          "WinterLocation": "MP 137"
        }
      ]
    }
  ],
  "Tutorials": [],
  "Practicals": []
}