{
  "CourseName": "MGR301H1-S",
  "Term": "S",
  "Lectures": [
    {
      "MeetingCode": "LEC0101",
      "Instructor": "Aravossitas, T.",
      "Times": [
        {
          "Day": "Tuesday",
          "StartTime": 13.0,
          "EndTime": 15.0,
          "FallLocation": null,
          "WinterLocation": "TF 103"
        },
        {
          "Day": "Thursday",
          "StartTime": 13.0,
          "EndTime": 15.0,
          "FallLocation": null,
          "WinterLocation": "TF 103"
        }
      ]
    }
  ],
  "Tutorials": [],
  "Practicals": []
}