{
  "CourseName": "RLG204H1-S",
  "Term": "S",
  "Lectures": [
    {
      "MeetingCode": "LEC5101",
      "Instructor": "Silvers, L.",
      "Times": [
        {
          "Day": "Thursday",
          "StartTime": 17.0,
          "EndTime": 19.0,
          "FallLocation": null,
          "WinterLocation": "SS 1070"
        }
      ]
    }
  ],
  "Tutorials": [
    {
      "MeetingCode": "TUT0101",
      "Instructor": "—",
      "Times": [
        {
          "Day": "Thursday",
          "StartTime": 16.0,
          "EndTime": 17.0,
          "FallLocation": null,
          "WinterLocation": "BF 215"
        }
      ]
    },
    {
      "MeetingCode": "TUT5101",
      "Instructor": "—",
      "Times": [
        {
          "Day": "Thursday",
          "StartTime": 19.0,
          "EndTime": 20.0,
          "FallLocation": null,
          "WinterLocation": "SS 2111"
        }
      ]
    }
  ],
  "Practicals": []
}